cmeta/__init__.py
cmeta/exceptions.py
cmeta/models.py
cmeta/parser.py
cmeta/transform.py
cmeta/versions.py
nuklai_cmeta-0.1.0.dist-info/METADATA
nuklai_cmeta-0.1.0.dist-info/WHEEL
nuklai_cmeta-0.1.0.dist-info/licenses/LICENSE
nuklai_cmeta-0.1.0.dist-info/RECORD
