Metadata-Version: 2.4
Name: nuklai-cmeta
Version: 0.1.0
Summary: CMeta v1: compact metadata format with JSON transforms
Project-URL: Homepage, https://github.com/nuklai/cmeta
Author-email: Matthijs de Vries <matthijs@nukl.ai>
License: MIT
License-File: LICENSE
Requires-Python: >=3.10
Provides-Extra: dev
Requires-Dist: mypy>=1.10; extra == 'dev'
Requires-Dist: pytest>=8; extra == 'dev'
Requires-Dist: ruff>=0.5; extra == 'dev'
